ThiagoCalc/ThiagoCalc.py
ThiagoCalc/__init__.py
ThiagoCalc-0.2.0.dist-info/METADATA
ThiagoCalc-0.2.0.dist-info/WHEEL
ThiagoCalc-0.2.0.dist-info/top_level.txt
ThiagoCalc-0.2.0.dist-info/RECORD
